setup.py
web_scraper_ro/__init__.py
web_scraper_ro/web_scraper_ro.py
web_scraper_ro.egg-info/PKG-INFO
web_scraper_ro.egg-info/SOURCES.txt
web_scraper_ro.egg-info/dependency_links.txt
web_scraper_ro.egg-info/not-zip-safe
web_scraper_ro.egg-info/top_level.txt