Metadata-Version: 2.1
Name: web-scraper-ro
Version: 0.1
Summary: Scrape any given website
Author: Rohit Singh
